quantum_pqc_migration_toolkit/__init__.py
quantum_pqc_migration_toolkit/__main__.py
quantum_pqc_migration_toolkit/cli.py
quantum_pqc_migration_toolkit/io.py
quantum_pqc_migration_toolkit/models.py
quantum_pqc_migration_toolkit/planner.py
quantum_pqc_migration_toolkit/risk.py
quantum_pqc_migration_toolkit/risk_params.py
quantum_pqc_migration_toolkit/simulate.py
quantum_pqc_migration_toolkit-0.1.0.dist-info/licenses/LICENSE
quantum_pqc_migration_toolkit-0.1.0.dist-info/METADATA
quantum_pqc_migration_toolkit-0.1.0.dist-info/WHEEL
quantum_pqc_migration_toolkit-0.1.0.dist-info/entry_points.txt
quantum_pqc_migration_toolkit-0.1.0.dist-info/top_level.txt
quantum_pqc_migration_toolkit-0.1.0.dist-info/RECORD
