Metadata-Version: 2.4
Name: quantum-pqc-migration-toolkit
Version: 0.1.0
Summary: A toolkit for assessing and planning organizational migration from classical public-key cryptography to post-quantum cryptographic algorithms
License: MIT
Project-URL: Homepage, https://github.com/quantum-pqc-migration-toolkit
Project-URL: Documentation, https://github.com/quantum-pqc-migration-toolkit#readme
Project-URL: Repository, https://github.com/quantum-pqc-migration-toolkit
Project-URL: Issues, https://github.com/quantum-pqc-migration-toolkit/issues
Keywords: post-quantum,cryptography,pqc,migration,quantum-safe,risk-assessment,nist,ml-kem,ml-dsa,cybersecurity
Classifier: Development Status :: 4 - Beta
Classifier: Intended Audience :: Developers
Classifier: Intended Audience :: Science/Research
Classifier: License :: OSI Approved :: MIT License
Classifier: Operating System :: OS Independent
Classifier: Programming Language :: Python :: 3
Classifier: Programming Language :: Python :: 3.9
Classifier: Programming Language :: Python :: 3.10
Classifier: Programming Language :: Python :: 3.11
Classifier: Programming Language :: Python :: 3.12
Classifier: Topic :: Security :: Cryptography
Classifier: Topic :: Scientific/Engineering
Requires-Python: >=3.9
License-File: LICENSE
Requires-Dist: pyyaml>=6.0
Requires-Dist: numpy>=1.21.0
Requires-Dist: pandas>=1.3.0
Requires-Dist: typer>=0.9.0
Requires-Dist: rich>=13.0.0
Provides-Extra: dev
Requires-Dist: pytest>=7.0.0; extra == "dev"
Requires-Dist: pytest-cov>=4.0.0; extra == "dev"
Requires-Dist: black>=23.0.0; extra == "dev"
Requires-Dist: ruff>=0.1.0; extra == "dev"
Requires-Dist: mypy>=1.0.0; extra == "dev"
Provides-Extra: notebook
Requires-Dist: jupyter>=1.0.0; extra == "notebook"
Requires-Dist: matplotlib>=3.5.0; extra == "notebook"
Requires-Dist: seaborn>=0.12.0; extra == "notebook"
Dynamic: license-file
